falconry/__init__.py
falconry/__main__.py
falconry/cli.py
falconry/job.py
falconry/manager.py
falconry/quick_job.py
falconry/run_simple.sh
falconry/schedd_wrapper.py
falconry/status.py
falconry-0.3.0.dist-info/METADATA
falconry-0.3.0.dist-info/WHEEL
falconry-0.3.0.dist-info/entry_points.txt
falconry-0.3.0.dist-info/licenses/LICENSE
falconry-0.3.0.dist-info/RECORD
