Metadata-Version: 2.4
Name: falconry
Version: 0.3.0
Summary: A lightweight python package to create and manage your HTCondor jobs.
Project-URL: Documentation, https://falconry.readthedocs.io/en/stable/
Project-URL: Repository, https://github.com/fnechans/falconry
Project-URL: Issues, https://github.com/fnechans/falconry/issues
Author-email: Filip Nechansky <filip.nechansky@protonmail.com>
License-File: LICENSE
Classifier: Development Status :: 4 - Beta
Classifier: License :: OSI Approved :: MIT License
Classifier: Programming Language :: Python :: 3.9
Classifier: Programming Language :: Python :: 3.10
Classifier: Programming Language :: Python :: 3.11
Classifier: Programming Language :: Python :: 3.12
Requires-Python: >=3.9
Requires-Dist: htcondor>=25
Requires-Dist: ijson>=3.3.0
